safethread/__init__.py
safethread/datatype/SafeBaseObj.py
safethread/datatype/SafeDict.py
safethread/datatype/SafeList.py
safethread/datatype/SafeQueue.py
safethread/datatype/SafeSet.py
safethread/datatype/SafeTuple.py
safethread/datatype/__init__.py
safethread/thread/Scheduler.py
safethread/thread/Subprocess.py
safethread/thread/ThreadBase.py
safethread/thread/__init__.py
safethread/utils/Factory.py
safethread/utils/FileHandler.py
safethread/utils/INIFileHandler.py
safethread/utils/Log.py
safethread/utils/Pipeline.py
safethread/utils/PipelineStage.py
safethread/utils/Publisher.py
safethread/utils/Regex.py
safethread/utils/Singleton.py
safethread/utils/Subscriber.py
safethread/utils/__init__.py
safethread/utils/utils.py
safethread-2.0.0.dist-info/LICENSE
safethread-2.0.0.dist-info/METADATA
safethread-2.0.0.dist-info/WHEEL
safethread-2.0.0.dist-info/top_level.txt
safethread-2.0.0.dist-info/RECORD
